inatroget/__init__.py
inatroget/config.py
inatroget/cookies.py
inatroget/entry.py
inatroget/get_info.py
inatroget/utils.py
inatroget-0.1.0.dist-info/METADATA
inatroget-0.1.0.dist-info/WHEEL
inatroget-0.1.0.dist-info/top_level.txt
inatroget-0.1.0.dist-info/RECORD
