Metadata-Version: 2.4
Name: inatroget
Version: 0.1.0
Summary: Lib for getting driver's information
Author: yannickRafael
Requires-Python: >=3.9
Requires-Dist: requests>=2.31
Requires-Dist: python-dotenv>=1.0
